[
    {
        "book_title": "婚夜，穷份暴露",
        "book_url": "https://fanqienovel.com/page/7029101480598572068?enter_from=stack-room"
    },
    {
        "book_title": "贵妃野茶！皇帝换宠？",
        "book_url": "https://fanqienovel.com/page/7089385506269563938?enter_from=stack-room"
    },
    {
        "book_title": "皇叔抢",
        "book_url": "https://fanqienovel.com/page/7054705290490416131?enter_from=stack-room"
    },
    {
        "book_title": "医婿",
        "book_url": "https://fanqienovel.com/page/6800308016882125835?enter_from=stack-room"
    },
    {
        "book_title": "穿越，冷煞掌宝",
        "book_url": "https://fanqienovel.com/page/7076003918399933470?enter_from=stack-room"
    },
    {
        "book_title": "穿荒，极品恶婆婆",
        "book_url": "https://fanqienovel.com/page/7033189390885063691?enter_from=stack-room"
    },
    {
        "book_title": "圣归，孙悟空誓必屠尽佛！",
        "book_url": "https://fanqienovel.com/page/6900994666632580109?enter_from=stack-room"
    },
    {
        "book_title": "引坠落",
        "book_url": "https://fanqienovel.com/page/7171016560285322270?enter_from=stack-room"
    },
    {
        "book_title": "惊爆！萌娃咪炸翻佬集团",
        "book_url": "https://fanqienovel.com/page/6990145055264607239?enter_from=stack-room"
    },
    {
        "book_title": "离医禁欲首辅夜夜宠",
        "book_url": "https://fanqienovel.com/page/7099393208404151335?enter_from=stack-room"
    },
    {
        "book_title": "宫，六宝抄",
        "book_url": "https://fanqienovel.com/page/6849646576604810244?enter_from=stack-room"
    },
    {
        "book_title": "府签千，投胎哭帝",
        "book_url": "https://fanqienovel.com/page/7088894840582179843?enter_from=stack-room"
    },
    {
        "book_title": "诡异播：限推演",
        "book_url": "https://fanqienovel.com/page/7113743406903331881?enter_from=stack-room"
    },
    {
        "book_title": "权宠医妃：腹黑赖",
        "book_url": "https://fanqienovel.com/page/6808520075990010893?enter_from=stack-room"
    },
    {
        "book_title": "市超级纨绔",
        "book_url": "https://fanqienovel.com/page/6992153315387640862?enter_from=stack-room"
    },
    {
        "book_title": "锦鲤团宠：医萌妃五半",
        "book_url": "https://fanqienovel.com/page/6903437590066629645?enter_from=stack-room"
    },
    {
        "book_title": "玄幻，顿悟混沌",
        "book_url": "https://fanqienovel.com/page/6838086444733434884?enter_from=stack-room"
    },
    {
        "book_title": "七零嫁糙汉：亿资空养崽崽",
        "book_url": "https://fanqienovel.com/page/7106139687604980775?enter_from=stack-room"
    },
    {
        "book_title": "七零，富乡撩爆纯糙汉",
        "book_url": "https://fanqienovel.com/page/7107908665159453696?enter_from=stack-room"
    },
    {
        "book_title": "殿",
        "book_url": "https://fanqienovel.com/page/6846366104005118983?enter_from=stack-room"
    },
    {
        "book_title": "市兵王",
        "book_url": "https://fanqienovel.com/page/1624193943574542?enter_from=stack-room"
    },
    {
        "book_title": "诱捕乖宝，野痞队强势攻陷",
        "book_url": "https://fanqienovel.com/page/7166179464945077260?enter_from=stack-room"
    },
    {
        "book_title": "古剑",
        "book_url": "https://fanqienovel.com/page/6795155356709293064?enter_from=stack-room"
    },
    {
        "book_title": "医妃睁，京城排队抢",
        "book_url": "https://fanqienovel.com/page/7045187140329671720?enter_from=stack-room"
    },
    {
        "book_title": "，闪婚豪继承",
        "book_url": "https://fanqienovel.com/page/7138337446931991565?enter_from=stack-room"
    },
    {
        "book_title": "婚！嫁渣哥甜爆崽",
        "book_url": "https://fanqienovel.com/page/7089648933554621472?enter_from=stack-room"
    },
    {
        "book_title": "反派：舔狗，舔骂渣！",
        "book_url": "https://fanqienovel.com/page/7171757005634276383?enter_from=stack-room"
    },
    {
        "book_title": "河志",
        "book_url": "https://fanqienovel.com/page/6967151997531196424?enter_from=stack-room"
    },
    {
        "book_title": "末：",
        "book_url": "https://fanqienovel.com/page/7051529986372537376?enter_from=stack-room"
    },
    {
        "book_title": "震惊！洞房夜丑妻绝帝",
        "book_url": "https://fanqienovel.com/page/7040248860622457892?enter_from=stack-room"
    },
    {
        "book_title": "灵泉修仙：农崽养妖怪",
        "book_url": "https://fanqienovel.com/page/7077416502973959202?enter_from=stack-room"
    },
    {
        "book_title": "穿七零，各佬组团孙",
        "book_url": "https://fanqienovel.com/page/7096014689892568072?enter_from=stack-room"
    },
    {
        "book_title": "请鬼差",
        "book_url": "https://fanqienovel.com/page/6942441629332540423?enter_from=stack-room"
    },
    {
        "book_title": "醒，醋精裁婚",
        "book_url": "https://fanqienovel.com/page/7164291254606367782?enter_from=stack-room"
    },
    {
        "book_title": "摄政王病娇，宠",
        "book_url": "https://fanqienovel.com/page/6830847364970843140?enter_from=stack-room"
    },
    {
        "book_title": "市：裁朋巨甜",
        "book_url": "https://fanqienovel.com/page/7143123489816316966?enter_from=stack-room"
    },
    {
        "book_title": "穿级佬拿炮灰剧",
        "book_url": "https://fanqienovel.com/page/7107249144346971149?enter_from=stack-room"
    },
    {
        "book_title": "穿越：狂妃宠",
        "book_url": "https://fanqienovel.com/page/7104468967250463777?enter_from=stack-room"
    },
    {
        "book_title": "七零空：糙汉穿娇青",
        "book_url": "https://fanqienovel.com/page/7123425336598989835?enter_from=stack-room"
    },
    {
        "book_title": "诱哄！阴鸷撩",
        "book_url": "https://fanqienovel.com/page/7110441868302748680?enter_from=stack-room"
    },
    {
        "book_title": "播：阴治愈，",
        "book_url": "https://fanqienovel.com/page/7008427473478093864?enter_from=stack-room"
    },
    {
        "book_title": "闪婚，娇妻甲捂",
        "book_url": "https://fanqienovel.com/page/7046283559580994593?enter_from=stack-room"
    },
    {
        "book_title": "穿继，侯府拼保胎",
        "book_url": "https://fanqienovel.com/page/7097213387943185439?enter_from=stack-room"
    },
    {
        "book_title": "，豪掌权宠",
        "book_url": "https://fanqienovel.com/page/7161765876935429132?enter_from=stack-room"
    },
    {
        "book_title": "镇驸爷",
        "book_url": "https://fanqienovel.com/page/6955825218392689678?enter_from=stack-room"
    },
    {
        "book_title": "惊！甲佬莲横踢竖卷",
        "book_url": "https://fanqienovel.com/page/7090217989345119239?enter_from=stack-room"
    },
    {
        "book_title": "祖祠签百，皇祖",
        "book_url": "https://fanqienovel.com/page/6911622068467403790?enter_from=stack-room"
    },
    {
        "book_title": "网游：隐藏息",
        "book_url": "https://fanqienovel.com/page/7026630823847660547?enter_from=stack-room"
    },
    {
        "book_title": "兵：创造恐怖幽灵",
        "book_url": "https://fanqienovel.com/page/6998372040163986432?enter_from=stack-room"
    },
    {
        "book_title": "乖，怕！病娇反派致撩宠配",
        "book_url": "https://fanqienovel.com/page/7177656316981152802?enter_from=stack-room"
    },
    {
        "book_title": "签圣：婆竟魔帝",
        "book_url": "https://fanqienovel.com/page/7047467760598649859?enter_from=stack-room"
    },
    {
        "book_title": "哭！疯批占！",
        "book_url": "https://fanqienovel.com/page/7172390699856301093?enter_from=stack-room"
    },
    {
        "book_title": "右级计算",
        "book_url": "https://fanqienovel.com/page/6833430353554705422?enter_from=stack-room"
    },
    {
        "book_title": "退队追火葬？爷爬！",
        "book_url": "https://fanqienovel.com/page/7182098972612234251?enter_from=stack-room"
    },
    {
        "book_title": "产五，闪婚单爸爸",
        "book_url": "https://fanqienovel.com/page/7135266939512818728?enter_from=stack-room"
    },
    {
        "book_title": "亿亿富翁，摊牌",
        "book_url": "https://fanqienovel.com/page/6841186317166971907?enter_from=stack-room"
    },
    {
        "book_title": "！穿渣爹妾妻！",
        "book_url": "https://fanqienovel.com/page/7078854050145373198?enter_from=stack-room"
    },
    {
        "book_title": "绝脸",
        "book_url": "https://fanqienovel.com/page/7160561094358993951?enter_from=stack-room"
    },
    {
        "book_title": "七零空：村凶糙汉宠",
        "book_url": "https://fanqienovel.com/page/7097413677216697352?enter_from=stack-room"
    },
    {
        "book_title": "穿恶洗",
        "book_url": "https://fanqienovel.com/page/6969913600760613901?enter_from=stack-room"
    },
    {
        "book_title": "球武：武功修炼",
        "book_url": "https://fanqienovel.com/page/6995009818402491426?enter_from=stack-room"
    },
    {
        "book_title": "阴沉沉反派懵",
        "book_url": "https://fanqienovel.com/page/7158690692951182336?enter_from=stack-room"
    },
    {
        "book_title": "刚，约影",
        "book_url": "https://fanqienovel.com/page/7105756538752470031?enter_from=stack-room"
    },
    {
        "book_title": "，君侯府拆",
        "book_url": "https://fanqienovel.com/page/7110188045189516291?enter_from=stack-room"
    },
    {
        "book_title": "啊，嘴！追福宝喂饭",
        "book_url": "https://fanqienovel.com/page/7082832498169744387?enter_from=stack-room"
    },
    {
        "book_title": "王侯",
        "book_url": "https://fanqienovel.com/page/7099655319621471269?enter_from=stack-room"
    },
    {
        "book_title": "，五哥哥哭求府",
        "book_url": "https://fanqienovel.com/page/6944717866725805092?enter_from=stack-room"
    },
    {
        "book_title": "传管局",
        "book_url": "https://fanqienovel.com/page/7038385168364604451?enter_from=stack-room"
    },
    {
        "book_title": "夺契约：陆宠",
        "book_url": "https://fanqienovel.com/page/6763492846096878606?enter_from=stack-room"
    },
    {
        "book_title": "狱：影帝黑粉",
        "book_url": "https://fanqienovel.com/page/7105950456471358478?enter_from=stack-room"
    },
    {
        "book_title": "凡欲仙",
        "book_url": "https://fanqienovel.com/page/6999435908046916621?enter_from=stack-room"
    },
    {
        "book_title": "谨慎凶狠",
        "book_url": "https://fanqienovel.com/page/7050311566700317730?enter_from=stack-room"
    },
    {
        "book_title": "洪荒：苟元凤腹，稳健",
        "book_url": "https://fanqienovel.com/page/7064547932506164235?enter_from=stack-room"
    },
    {
        "book_title": "怎办？迫杠精崽娘",
        "book_url": "https://fanqienovel.com/page/7135439682506066981?enter_from=stack-room"
    },
    {
        "book_title": "崽热搜，帝裁夜夜哄娃",
        "book_url": "https://fanqienovel.com/page/7031722528670223396?enter_from=stack-room"
    },
    {
        "book_title": "离婚球首富尖宠",
        "book_url": "https://fanqienovel.com/page/6994343518088989735?enter_from=stack-room"
    },
    {
        "book_title": "求婚拒，冷校强撩",
        "book_url": "https://fanqienovel.com/page/7035869621940915214?enter_from=stack-room"
    },
    {
        "book_title": "穿越六青",
        "book_url": "https://fanqienovel.com/page/7093120858784271375?enter_from=stack-room"
    },
    {
        "book_title": "枕囚宠：裁逃跑娘",
        "book_url": "https://fanqienovel.com/page/7030724287526865950?enter_from=stack-room"
    },
    {
        "book_title": "揉碎玫瑰",
        "book_url": "https://fanqienovel.com/page/7167980843841883171?enter_from=stack-room"
    },
    {
        "book_title": "断捐款，振兴华语坛",
        "book_url": "https://fanqienovel.com/page/7109754070230895657?enter_from=stack-room"
    },
    {
        "book_title": "封非歹，称贤王",
        "book_url": "https://fanqienovel.com/page/7114642482326932513?enter_from=stack-room"
    },
    {
        "book_title": "辍",
        "book_url": "https://fanqienovel.com/page/7172361878125939712?enter_from=stack-room"
    },
    {
        "book_title": "楚爷，热搜",
        "book_url": "https://fanqienovel.com/page/7073776238019480590?enter_from=stack-room"
    },
    {
        "book_title": "，婆惨",
        "book_url": "https://fanqienovel.com/page/7095533881125768206?enter_from=stack-room"
    },
    {
        "book_title": "：富翁",
        "book_url": "https://fanqienovel.com/page/6901924870733433863?enter_from=stack-room"
    },
    {
        "book_title": "甜爆！精撩哄佬",
        "book_url": "https://fanqienovel.com/page/7155414889563950087?enter_from=stack-room"
    },
    {
        "book_title": "酒醒，婚证",
        "book_url": "https://fanqienovel.com/page/7107922536511310861?enter_from=stack-room"
    },
    {
        "book_title": "破版玄幻，局修改级修",
        "book_url": "https://fanqienovel.com/page/7158783339954965517?enter_from=stack-room"
    },
    {
        "book_title": "校园王牌：佬扮猪虎",
        "book_url": "https://fanqienovel.com/page/7101691270392712225?enter_from=stack-room"
    },
    {
        "book_title": "局融合",
        "book_url": "https://fanqienovel.com/page/7090529522100997127?enter_from=stack-room"
    },
    {
        "book_title": "锁怀！娇妻步步落圈套",
        "book_url": "https://fanqienovel.com/page/7141295542729968677?enter_from=stack-room"
    },
    {
        "book_title": "洪荒：局限",
        "book_url": "https://fanqienovel.com/page/6988079856420391967?enter_from=stack-room"
    },
    {
        "book_title": "虐渣：假千超钱",
        "book_url": "https://fanqienovel.com/page/6881855310009469963?enter_from=stack-room"
    },
    {
        "book_title": "坏",
        "book_url": "https://fanqienovel.com/page/7012873192846920741?enter_from=stack-room"
    },
    {
        "book_title": "驯养疯批权臣：越娇，越撩！",
        "book_url": "https://fanqienovel.com/page/7111203503627832357?enter_from=stack-room"
    },
    {
        "book_title": "婚夜悔婚，抱娇妻香",
        "book_url": "https://fanqienovel.com/page/7148033757465807910?enter_from=stack-room"
    },
    {
        "book_title": "冲喜君香",
        "book_url": "https://fanqienovel.com/page/7003145452606458888?enter_from=stack-room"
    },
    {
        "book_title": "卿朝朝暮暮",
        "book_url": "https://fanqienovel.com/page/7096778156639521823?enter_from=stack-room"
    },
    {
        "book_title": "抄流？慌，咱空囤粮",
        "book_url": "https://fanqienovel.com/page/7153870234556828708?enter_from=stack-room"
    }
]